cezve/__init__.py
cezve-0.0.1.dist-info/METADATA
cezve-0.0.1.dist-info/WHEEL
cezve-0.0.1.dist-info/top_level.txt
cezve-0.0.1.dist-info/RECORD
