Metadata-Version: 2.1
Name: cezve
Version: 0.0.1
Summary: A really small web framework
Home-page: https://github.com/emersonmx/cezve
Author: Emerson Max de Medeiros Silva
Author-email: emersonmx@gmail.com
License: UNKNOWN
Platform: UNKNOWN
Classifier: Programming Language :: Python :: 3
Classifier: License :: OSI Approved :: MIT License
Classifier: Operating System :: OS Independent
Requires-Python: >=3.6
